[
{"r":17095,"d":0.8,"s":0.013,"a":-0.014},
{"r":17240,"d":0.9,"s":0.006,"a":-0.012},
{"r":17376,"d":0.8,"s":0,"a":-0.007},
{"r":17604,"d":0.7,"s":-0.008,"a":-0.002},
{"r":17653,"d":0.6,"s":-0.008,"a":-0.002},
{"r":17682,"d":0.5,"s":-0.009,"a":-0.002},
{"r":17707,"d":0.4,"s":-0.009,"a":-0.002},
{"r":17734,"d":0.3,"s":-0.009,"a":-0.003},
{"r":17769,"d":0.2,"s":-0.009,"a":-0.003},
{"r":17926,"d":0.3,"s":-0.011,"a":-0.004},
{"r":18109,"d":0.4,"s":-0.014,"a":-0.002},
{"r":18140,"d":0.3,"s":-0.015,"a":-0.001},
{"r":18194,"d":0.4,"s":-0.015,"a":-0.001},
{"r":18340,"d":0.3,"s":-0.017,"a":-0.001},
{"r":18395,"d":0.2,"s":-0.017,"a":-0.002},
{"r":18459,"d":0.1,"s":-0.017,"a":-0.003},
{"r":18599,"d":0.2,"s":-0.018,"a":-0.003},
{"r":18691,"d":0.3,"s":-0.02,"a":-0.003},
{"r":19089,"d":0.2,"s":-0.024,"a":0.001},
{"r":19208,"d":0.1,"s":-0.024,"a":0.001},
{"r":19279,"d":0,"s":-0.024,"a":0.001},
{"r":19803,"d":-0.1,"s":-0.022,"a":0.003},
{"r":19925,"d":-0.2,"s":-0.02,"a":0.001},
{"r":20127,"d":-0.1,"s":-0.019,"a":-0.001},
{"r":20237,"d":0,"s":-0.019,"a":-0.002},
{"r":20403,"d":0.1,"s":-0.02,"a":-0.004},
{"r":20611,"d":0.2,"s":-0.024,"a":-0.005},
{"r":21060,"d":0.3,"s":-0.034,"a":-0.008},
{"r":21467,"d":0.2,"s":-0.045,"a":-0.005},
{"r":21557,"d":0.1,"s":-0.047,"a":-0.005},
{"r":21896,"d":0,"s":-0.053,"a":-0.004},
{"r":22226,"d":-0.1,"s":-0.059,"a":-0.004},
{"r":22476,"d":0,"s":-0.063,"a":-0.005},
{"r":22548,"d":-0.1,"s":-0.064,"a":-0.004},
{"r":22650,"d":0,"s":-0.067,"a":-0.003},
{"r":22670,"d":-0.1,"s":-0.067,"a":-0.002},
{"r":22925,"d":-0.2,"s":-0.07,"a":0.005},
{"r":22983,"d":-0.3,"s":-0.07,"a":0.006},
{"r":23026,"d":-0.4,"s":-0.069,"a":0.007},
{"r":23085,"d":-0.5,"s":-0.069,"a":0.007},
{"r":23124,"d":-0.6,"s":-0.068,"a":0.007},
{"r":23173,"d":-0.7,"s":-0.067,"a":0.007},
{"r":23246,"d":-0.8,"s":-0.065,"a":0.007},
{"r":23326,"d":-0.9,"s":-0.063,"a":0.007},
{"r":23508,"d":-0.8,"s":-0.058,"a":0.006},
{"r":23619,"d":-0.9,"s":-0.056,"a":0.006},
{"r":23946,"d":-0.8,"s":-0.05,"a":0.005},
{"r":24140,"d":-0.9,"s":-0.047,"a":0.006},
{"r":24211,"d":-1,"s":-0.045,"a":0.007},
{"r":24321,"d":-0.9,"s":-0.043,"a":0.008},
{"r":24460,"d":-1,"s":-0.04,"a":0.011},
{"r":24575,"d":-1.1,"s":-0.036,"a":0.012},
{"r":24687,"d":-1.2,"s":-0.032,"a":0.013},
{"r":24786,"d":-1.3,"s":-0.028,"a":0.014},
{"r":24906,"d":-1.4,"s":-0.023,"a":0.014},
{"r":25399,"d":-1.3,"s":-0.002,"a":0.005},
{"r":25472,"d":-1.2,"s":0,"a":0.004},
{"r":25589,"d":-1.1,"s":0.001,"a":0.001},
{"r":25719,"d":-1,"s":0.002,"a":0},
{"r":25772,"d":-0.9,"s":0.003,"a":0},
{"r":25829,"d":-0.8,"s":0.003,"a":0},
{"r":26068,"d":-0.7,"s":0.002,"a":-0.001},
{"r":26663,"d":-0.8,"s":0,"a":0.006},
{"r":26723,"d":-0.9,"s":0.001,"a":0.006},
{"r":26758,"d":-1,"s":0.002,"a":0.006},
{"r":26802,"d":-1.1,"s":0.003,"a":0.006},
{"r":27060,"d":-1,"s":0.008,"a":0.01},
{"r":27169,"d":-1.1,"s":0.011,"a":0.012},
{"r":27264,"d":-1.2,"s":0.014,"a":0.013},
{"r":27416,"d":-1.3,"s":0.02,"a":0.013},
{"r":27518,"d":-1.4,"s":0.025,"a":0.012},
{"r":27761,"d":-1.3,"s":0.035,"a":0.01},
{"r":27859,"d":-1.2,"s":0.039,"a":0.009},
{"r":28163,"d":-1.1,"s":0.048,"a":0.004},
{"r":28262,"d":-1,"s":0.05,"a":0.002},
{"r":28334,"d":-0.9,"s":0.051,"a":0.001},
{"r":28414,"d":-0.8,"s":0.051,"a":0.001},
{"r":28540,"d":-0.7,"s":0.052,"a":0.001},
{"r":28645,"d":-0.6,"s":0.052,"a":0.001},
{"r":28833,"d":-0.7,"s":0.053,"a":0.001},
{"r":29006,"d":-0.6,"s":0.053,"a":0.001},
{"r":29067,"d":-0.5,"s":0.053,"a":0},
{"r":29179,"d":-0.6,"s":0.054,"a":0},
{"r":29351,"d":-0.5,"s":0.054,"a":0},
{"r":29452,"d":-0.4,"s":0.053,"a":0},
{"r":29704,"d":-0.5,"s":0.053,"a":0},
{"r":29840,"d":-0.4,"s":0.053,"a":0},
{"r":30029,"d":-0.3,"s":0.053,"a":0.001},
{"r":30190,"d":-0.4,"s":0.053,"a":0.002},
{"r":30369,"d":-0.3,"s":0.054,"a":0.006},
{"r":30490,"d":-0.4,"s":0.055,"a":0.009},
{"r":30605,"d":-0.5,"s":0.058,"a":0.012},
{"r":30689,"d":-0.6,"s":0.06,"a":0.013},
{"r":30790,"d":-0.7,"s":0.064,"a":0.013},
{"r":30881,"d":-0.8,"s":0.068,"a":0.013},
{"r":31200,"d":-0.7,"s":0.082,"a":0.008},
{"r":31293,"d":-0.6,"s":0.085,"a":0.007},
{"r":31354,"d":-0.5,"s":0.086,"a":0.006},
{"r":31494,"d":-0.4,"s":0.09,"a":0.003},
{"r":31616,"d":-0.3,"s":0.092,"a":0.002},
{"r":31686,"d":-0.2,"s":0.092,"a":0.002},
{"r":31765,"d":-0.1,"s":0.093,"a":0.002},
{"r":31872,"d":0,"s":0.094,"a":0.002},
{"r":32185,"d":0.1,"s":0.096,"a":-0.001},
{"r":32393,"d":0.2,"s":0.095,"a":-0.004},
{"r":32450,"d":0.3,"s":0.094,"a":-0.004},
{"r":32508,"d":0.4,"s":0.094,"a":-0.004},
{"r":32587,"d":0.5,"s":0.092,"a":-0.005},
{"r":32737,"d":0.6,"s":0.089,"a":-0.005},
{"r":33009,"d":0.7,"s":0.084,"a":-0.005},
{"r":33323,"d":0.8,"s":0.078,"a":-0.006},
{"r":33576,"d":0.9,"s":0.072,"a":-0.004},
{"r":33896,"d":0.8,"s":0.067,"a":0},
{"r":33986,"d":0.7,"s":0.067,"a":0.001},
{"r":34363,"d":0.6,"s":0.068,"a":0.001},
{"r":34558,"d":0.7,"s":0.069,"a":-0.002},
{"r":34678,"d":0.8,"s":0.068,"a":-0.002},
{"r":34740,"d":0.9,"s":0.068,"a":-0.001},
{"r":34802,"d":1,"s":0.067,"a":0},
{"r":34881,"d":1.1,"s":0.066,"a":0},
{"r":34947,"d":1,"s":0.066,"a":0},
{"r":35078,"d":0.9,"s":0.066,"a":0},
{"r":35330,"d":1,"s":0.065,"a":-0.003},
{"r":35454,"d":1.1,"s":0.064,"a":-0.005},
{"r":35572,"d":1.2,"s":0.062,"a":-0.006},
{"r":35695,"d":1.3,"s":0.059,"a":-0.007},
{"r":35838,"d":1.4,"s":0.056,"a":-0.009},
{"r":35997,"d":1.5,"s":0.051,"a":-0.009},
{"r":36129,"d":1.6,"s":0.046,"a":-0.008},
{"r":36300,"d":1.5,"s":0.041,"a":-0.007},
{"r":36425,"d":1.6,"s":0.037,"a":-0.006},
{"r":36600,"d":1.5,"s":0.033,"a":-0.003},
{"r":36779,"d":1.4,"s":0.03,"a":-0.002},
{"r":36995,"d":1.3,"s":0.028,"a":-0.004},
{"r":37198,"d":1.4,"s":0.025,"a":-0.007},
{"r":37284,"d":1.5,"s":0.023,"a":-0.007},
{"r":37351,"d":1.6,"s":0.021,"a":-0.006},
{"r":37422,"d":1.7,"s":0.019,"a":-0.005},
{"r":37613,"d":1.6,"s":0.014,"a":-0.002},
{"r":37695,"d":1.5,"s":0.013,"a":-0.001},
{"r":37819,"d":1.4,"s":0.012,"a":0},
{"r":37943,"d":1.3,"s":0.012,"a":0},
{"r":38053,"d":1.4,"s":0.011,"a":0},
{"r":38174,"d":1.3,"s":0.011,"a":-0.001},
{"r":38376,"d":1.4,"s":0.01,"a":-0.003},
{"r":38569,"d":1.5,"s":0.007,"a":-0.004},
{"r":38754,"d":1.6,"s":0.004,"a":-0.004},
{"r":38833,"d":1.5,"s":0.002,"a":-0.003},
{"r":38846,"d":1.6,"s":0.002,"a":-0.003},
{"r":38963,"d":1.5,"s":0,"a":-0.002},
{"r":39254,"d":1.4,"s":-0.002,"a":-0.005},
{"r":39387,"d":1.5,"s":-0.004,"a":-0.007},
{"r":39471,"d":1.6,"s":-0.006,"a":-0.007},
{"r":39628,"d":1.7,"s":-0.011,"a":-0.006},
{"r":39873,"d":1.6,"s":-0.017,"a":-0.004},
{"r":40044,"d":1.5,"s":-0.02,"a":-0.004},
{"r":40457,"d":1.4,"s":-0.025,"a":-0.002},
{"r":40513,"d":1.3,"s":-0.025,"a":-0.002},
{"r":40743,"d":1.4,"s":-0.028,"a":-0.004},
{"r":40927,"d":1.5,"s":-0.031,"a":-0.004},
{"r":40972,"d":1.4,"s":-0.031,"a":-0.004},
{"r":41078,"d":1.5,"s":-0.033,"a":-0.003},
{"r":41114,"d":1.4,"s":-0.034,"a":-0.003},
{"r":41425,"d":1.3,"s":-0.038,"a":-0.003},
{"r":41692,"d":1.4,"s":-0.042,"a":-0.002},
{"r":41719,"d":1.3,"s":-0.042,"a":-0.002},
{"r":42002,"d":1.2,"s":-0.045,"a":0},
{"r":42088,"d":1.1,"s":-0.045,"a":0},
{"r":42220,"d":1,"s":-0.046,"a":0.001},
{"r":42301,"d":1.1,"s":-0.046,"a":0.002},
{"r":42499,"d":1,"s":-0.045,"a":0.005},
{"r":42554,"d":0.9,"s":-0.044,"a":0.004},
{"r":42637,"d":0.8,"s":-0.043,"a":0.003},
{"r":42705,"d":0.7,"s":-0.042,"a":0.001},
{"r":42946,"d":0.8,"s":-0.04,"a":-0.006},
{"r":43000,"d":0.9,"s":-0.041,"a":-0.007},
{"r":43029,"d":1,"s":-0.041,"a":-0.007},
{"r":43070,"d":1.1,"s":-0.042,"a":-0.008},
{"r":43180,"d":1.2,"s":-0.045,"a":-0.009},
{"r":43291,"d":1.3,"s":-0.048,"a":-0.009},
{"r":43654,"d":1.4,"s":-0.061,"a":-0.009},
{"r":43662,"d":1.3,"s":-0.061,"a":-0.009},
{"r":43856,"d":1.2,"s":-0.068,"a":-0.006},
{"r":44069,"d":1.1,"s":-0.073,"a":-0.003},
{"r":44154,"d":1,"s":-0.075,"a":-0.001},
{"r":44300,"d":0.9,"s":-0.077,"a":0},
{"r":44366,"d":0.8,"s":-0.077,"a":0},
{"r":44428,"d":0.7,"s":-0.077,"a":0},
{"r":44485,"d":0.6,"s":-0.077,"a":0},
{"r":44707,"d":0.7,"s":-0.078,"a":0},
{"r":44785,"d":0.6,"s":-0.078,"a":0},
{"r":44895,"d":0.5,"s":-0.078,"a":0},
{"r":45482,"d":0.4,"s":-0.08,"a":0.004},
{"r":45568,"d":0.3,"s":-0.079,"a":0.004},
{"r":45614,"d":0.2,"s":-0.078,"a":0.003},
{"r":45680,"d":0.1,"s":-0.078,"a":0.003},
{"r":46121,"d":0.2,"s":-0.074,"a":0.002},
{"r":46179,"d":0.1,"s":-0.073,"a":0.002},
{"r":46319,"d":0,"s":-0.072,"a":0.002},
{"r":46954,"d":-0.1,"s":-0.068,"a":0.006},
{"r":47067,"d":-0.2,"s":-0.066,"a":0.007},
{"r":47136,"d":-0.3,"s":-0.065,"a":0.007},
{"r":47326,"d":-0.4,"s":-0.061,"a":0.006},
{"r":47441,"d":-0.5,"s":-0.058,"a":0.004},
{"r":47592,"d":-0.4,"s":-0.055,"a":0.001},
{"r":47691,"d":-0.3,"s":-0.055,"a":0},
{"r":47823,"d":-0.2,"s":-0.054,"a":0.001},
{"r":48158,"d":-0.3,"s":-0.053,"a":0.01},
{"r":48214,"d":-0.4,"s":-0.051,"a":0.011},
{"r":48261,"d":-0.5,"s":-0.05,"a":0.012},
{"r":48318,"d":-0.6,"s":-0.048,"a":0.013},
{"r":48414,"d":-0.7,"s":-0.045,"a":0.014},
{"r":48467,"d":-0.8,"s":-0.042,"a":0.014},
{"r":48531,"d":-0.9,"s":-0.039,"a":0.015},
{"r":48652,"d":-1,"s":-0.034,"a":0.014},
{"r":49057,"d":-0.9,"s":-0.016,"a":0.01},
{"r":49171,"d":-0.8,"s":-0.012,"a":0.01},
{"r":49479,"d":-0.9,"s":-0.001,"a":0.011},
{"r":49898,"d":-0.8,"s":0.013,"a":0.013},
{"r":50000,"d":-0.9,"s":0.018,"a":0.013},
{"r":50126,"d":-1,"s":0.023,"a":0.012},
{"r":50406,"d":-0.9,"s":0.035,"a":0.005},
{"r":50503,"d":-0.8,"s":0.037,"a":0.003},
{"r":50565,"d":-0.7,"s":0.039,"a":0.002},
{"r":50626,"d":-0.6,"s":0.039,"a":0.001},
{"r":50696,"d":-0.5,"s":0.04,"a":0},
{"r":50802,"d":-0.4,"s":0.041,"a":0},
{"r":50857,"d":-0.3,"s":0.041,"a":0},
{"r":51097,"d":-0.2,"s":0.04,"a":0.001},
{"r":51372,"d":-0.3,"s":0.041,"a":0.003},
{"r":51683,"d":-0.4,"s":0.044,"a":0.005},
{"r":52042,"d":-0.3,"s":0.05,"a":0.006},
{"r":52137,"d":-0.2,"s":0.051,"a":0.008},
{"r":52257,"d":-0.3,"s":0.053,"a":0.01},
{"r":52348,"d":-0.4,"s":0.056,"a":0.011},
{"r":52431,"d":-0.5,"s":0.059,"a":0.011},
{"r":52571,"d":-0.6,"s":0.064,"a":0.009},
{"r":52681,"d":-0.5,"s":0.068,"a":0.008},
{"r":52869,"d":-0.4,"s":0.074,"a":0.007},
{"r":52926,"d":-0.3,"s":0.075,"a":0.007},
{"r":52983,"d":-0.2,"s":0.076,"a":0.007},
{"r":53062,"d":-0.1,"s":0.078,"a":0.006},
{"r":53121,"d":-0.2,"s":0.079,"a":0.006},
{"r":53185,"d":-0.3,"s":0.081,"a":0.005},
{"r":53287,"d":-0.2,"s":0.083,"a":0.004},
{"r":53360,"d":-0.1,"s":0.084,"a":0.003},
{"r":53410,"d":0,"s":0.085,"a":0.003},
{"r":53464,"d":-0.1,"s":0.086,"a":0.002},
{"r":53517,"d":0,"s":0.086,"a":0.002},
{"r":53652,"d":0.1,"s":0.088,"a":0.002},
{"r":53706,"d":0.2,"s":0.088,"a":0.002},
{"r":54002,"d":0.3,"s":0.09,"a":0.001},
{"r":54195,"d":0.4,"s":0.09,"a":0.001},
{"r":54592,"d":0.5,"s":0.091,"a":-0.002},
{"r":54776,"d":0.6,"s":0.09,"a":-0.005},
{"r":54853,"d":0.7,"s":0.089,"a":-0.006},
{"r":54899,"d":0.8,"s":0.088,"a":-0.006},
{"r":54947,"d":0.9,"s":0.087,"a":-0.005},
{"r":55061,"d":1,"s":0.084,"a":-0.004},
{"r":55432,"d":0.9,"s":0.079,"a":0},
{"r":55514,"d":0.8,"s":0.079,"a":-0.001},
{"r":55691,"d":0.9,"s":0.078,"a":-0.003},
{"r":55826,"d":1,"s":0.076,"a":-0.005},
{"r":55981,"d":1.1,"s":0.074,"a":-0.006},
{"r":56113,"d":1.2,"s":0.071,"a":-0.007},
{"r":56186,"d":1.3,"s":0.069,"a":-0.008},
{"r":56344,"d":1.4,"s":0.065,"a":-0.008},
{"r":56671,"d":1.5,"s":0.055,"a":-0.006},
{"r":56814,"d":1.4,"s":0.052,"a":-0.005},
{"r":57521,"d":1.5,"s":0.038,"a":-0.007},
{"r":57760,"d":1.6,"s":0.032,"a":-0.009},
{"r":57921,"d":1.7,"s":0.026,"a":-0.009},
{"r":58004,"d":1.8,"s":0.023,"a":-0.009},
{"r":58060,"d":1.7,"s":0.021,"a":-0.008},
{"r":58256,"d":1.8,"s":0.015,"a":-0.004},
{"r":58333,"d":1.7,"s":0.013,"a":-0.003},
{"r":58441,"d":1.6,"s":0.011,"a":-0.004},
{"r":58486,"d":1.5,"s":0.011,"a":-0.004},
{"r":58536,"d":1.4,"s":0.01,"a":-0.004},
{"r":58683,"d":1.5,"s":0.008,"a":-0.004},
{"r":58839,"d":1.6,"s":0.005,"a":-0.003},
{"r":58971,"d":1.5,"s":0.003,"a":-0.002},
{"r":59142,"d":1.4,"s":0.001,"a":-0.003},
{"r":59355,"d":1.5,"s":0,"a":-0.002},
{"r":59660,"d":1.4,"s":-0.004,"a":0.001},
{"r":59789,"d":1.3,"s":-0.004,"a":0.002},
{"r":60019,"d":1.2,"s":-0.002,"a":0},
{"r":60100,"d":1.1,"s":-0.002,"a":-0.002},
{"r":60162,"d":1.2,"s":-0.002,"a":-0.003},
{"r":60264,"d":1.3,"s":-0.003,"a":-0.004},
{"r":60346,"d":1.4,"s":-0.004,"a":-0.005},
{"r":60430,"d":1.5,"s":-0.005,"a":-0.005},
{"r":60527,"d":1.6,"s":-0.007,"a":-0.005},
{"r":60661,"d":1.5,"s":-0.01,"a":-0.004},
{"r":60861,"d":1.6,"s":-0.013,"a":-0.004},
{"r":60922,"d":1.5,"s":-0.014,"a":-0.003},
{"r":61242,"d":1.4,"s":-0.019,"a":-0.001},
{"r":61405,"d":1.3,"s":-0.02,"a":-0.002},
{"r":61675,"d":1.4,"s":-0.022,"a":-0.005},
{"r":61901,"d":1.5,"s":-0.027,"a":-0.005},
{"r":62164,"d":1.4,"s":-0.032,"a":-0.005},
{"r":62513,"d":1.5,"s":-0.039,"a":-0.006},
{"r":62785,"d":1.4,"s":-0.046,"a":-0.007},
{"r":63398,"d":1.3,"s":-0.061,"a":-0.002},
{"r":63488,"d":1.2,"s":-0.062,"a":-0.001},
{"r":63552,"d":1.1,"s":-0.063,"a":-0.001},
{"r":63732,"d":1,"s":-0.064,"a":0.001},
{"r":63968,"d":0.9,"s":-0.064,"a":0.003},
{"r":64034,"d":0.8,"s":-0.064,"a":0.003},
{"r":64098,"d":0.7,"s":-0.063,"a":0.003},
{"r":64409,"d":0.6,"s":-0.06,"a":0.001},
{"r":64586,"d":0.7,"s":-0.059,"a":-0.001},
{"r":64789,"d":0.8,"s":-0.06,"a":-0.002},
{"r":65172,"d":0.7,"s":-0.063,"a":-0.003},
{"r":65371,"d":0.8,"s":-0.066,"a":-0.003},
{"r":65559,"d":0.7,"s":-0.068,"a":-0.003},
{"r":65947,"d":0.6,"s":-0.074,"a":-0.004},
{"r":66631,"d":0.5,"s":-0.085,"a":0},
{"r":66715,"d":0.4,"s":-0.086,"a":0},
{"r":66787,"d":0.3,"s":-0.086,"a":0},
{"r":66981,"d":0.2,"s":-0.087,"a":0.002},
{"r":67053,"d":0.1,"s":-0.086,"a":0.002},
{"r":67266,"d":0,"s":-0.085,"a":0.002},
{"r":67419,"d":-0.1,"s":-0.084,"a":0.002},
{"r":67978,"d":-0.2,"s":-0.081,"a":0.002},
{"r":68090,"d":-0.3,"s":-0.08,"a":0.002},
{"r":68102,"d":-0.2,"s":-0.08,"a":0.001},
{"r":68215,"d":-0.3,"s":-0.079,"a":0.001},
{"r":68530,"d":-0.2,"s":-0.079,"a":0},
{"r":68656,"d":-0.3,"s":-0.079,"a":0},
{"r":68725,"d":-0.4,"s":-0.079,"a":0},
{"r":68769,"d":-0.3,"s":-0.078,"a":0},
{"r":68869,"d":-0.4,"s":-0.078,"a":0},
{"r":69401,"d":-0.5,"s":-0.077,"a":0.011},
{"r":69458,"d":-0.6,"s":-0.076,"a":0.012},
{"r":69509,"d":-0.7,"s":-0.074,"a":0.012},
{"r":69544,"d":-0.8,"s":-0.073,"a":0.012},
{"r":69583,"d":-0.9,"s":-0.071,"a":0.012},
{"r":69621,"d":-1,"s":-0.07,"a":0.012},
{"r":69663,"d":-1.1,"s":-0.068,"a":0.012},
{"r":69729,"d":-1.2,"s":-0.065,"a":0.011},
{"r":69914,"d":-1.1,"s":-0.058,"a":0.011},
{"r":70226,"d":-1.2,"s":-0.047,"a":0.008},
{"r":70402,"d":-1.1,"s":-0.041,"a":0.006},
{"r":70581,"d":-1,"s":-0.037,"a":0.006},
{"r":70960,"d":-1.1,"s":-0.029,"a":0.01},
{"r":71116,"d":-1.2,"s":-0.024,"a":0.009},
{"r":71178,"d":-1.3,"s":-0.022,"a":0.008},
{"r":71352,"d":-1.2,"s":-0.017,"a":0.006},
{"r":71488,"d":-1.1,"s":-0.014,"a":0.006},
{"r":72210,"d":-1.2,"s":0.001,"a":0.009},
{"r":72403,"d":-1.3,"s":0.007,"a":0.007},
{"r":72643,"d":-1.2,"s":0.013,"a":0.002},
{"r":72704,"d":-1.1,"s":0.014,"a":0.001},
{"r":72758,"d":-1,"s":0.014,"a":0},
{"r":72899,"d":-0.9,"s":0.015,"a":0},
{"r":72974,"d":-0.8,"s":0.015,"a":0},
{"r":73163,"d":-0.7,"s":0.014,"a":0.005},
{"r":73255,"d":-0.8,"s":0.014,"a":0.008},
{"r":73394,"d":-0.9,"s":0.017,"a":0.012},
{"r":73453,"d":-1,"s":0.019,"a":0.013},
{"r":73494,"d":-1.1,"s":0.02,"a":0.013},
{"r":73535,"d":-1.2,"s":0.022,"a":0.014},
{"r":73586,"d":-1.3,"s":0.024,"a":0.014},
{"r":73681,"d":-1.4,"s":0.028,"a":0.013},
{"r":73986,"d":-1.3,"s":0.041,"a":0.007},
{"r":74103,"d":-1.2,"s":0.045,"a":0.005},
{"r":74194,"d":-1.1,"s":0.047,"a":0.005},
{"r":74256,"d":-1,"s":0.048,"a":0.005},
{"r":74328,"d":-0.9,"s":0.049,"a":0.006},
{"r":74400,"d":-0.8,"s":0.05,"a":0.007},
{"r":74467,"d":-0.9,"s":0.051,"a":0.008},
{"r":74772,"d":-1,"s":0.059,"a":0.01},
{"r":74846,"d":-1.1,"s":0.061,"a":0.009},
{"r":74981,"d":-1.2,"s":0.066,"a":0.008},
{"r":74991,"d":-1.1,"s":0.066,"a":0.008},
{"r":75099,"d":-1,"s":0.07,"a":0.007},
{"r":75154,"d":-0.9,"s":0.071,"a":0.007},
{"r":75326,"d":-0.8,"s":0.075,"a":0.006},
{"r":75635,"d":-0.7,"s":0.082,"a":0.004},
{"r":75743,"d":-0.6,"s":0.083,"a":0.004},
{"r":75851,"d":-0.5,"s":0.085,"a":0.005},
{"r":76210,"d":-0.6,"s":0.091,"a":0.003},
{"r":76334,"d":-0.5,"s":0.093,"a":0.001},
{"r":76413,"d":-0.4,"s":0.093,"a":0},
{"r":76486,"d":-0.3,"s":0.094,"a":0},
{"r":76536,"d":-0.2,"s":0.094,"a":0},
{"r":76598,"d":-0.1,"s":0.094,"a":0},
{"r":76935,"d":0,"s":0.093,"a":0},
{"r":77369,"d":0.1,"s":0.093,"a":0},
{"r":77454,"d":0.2,"s":0.093,"a":0},
{"r":77547,"d":0.3,"s":0.093,"a":0},
{"r":77592,"d":0.2,"s":0.093,"a":0},
{"r":77907,"d":0.3,"s":0.092,"a":-0.003},
{"r":78045,"d":0.4,"s":0.091,"a":-0.003},
{"r":78144,"d":0.5,"s":0.089,"a":-0.003},
{"r":78242,"d":0.6,"s":0.088,"a":-0.002},
{"r":78455,"d":0.5,"s":0.086,"a":-0.002},
{"r":78528,"d":0.6,"s":0.085,"a":-0.001},
{"r":78664,"d":0.5,"s":0.084,"a":-0.001},
{"r":78685,"d":0.6,"s":0.084,"a":-0.001},
{"r":78844,"d":0.7,"s":0.082,"a":-0.002},
{"r":78921,"d":0.6,"s":0.082,"a":-0.003},
{"r":79027,"d":0.7,"s":0.081,"a":-0.006},
{"r":79050,"d":0.6,"s":0.081,"a":-0.006},
{"r":79064,"d":0.7,"s":0.08,"a":-0.007},
{"r":79174,"d":0.8,"s":0.078,"a":-0.01},
{"r":79262,"d":0.9,"s":0.076,"a":-0.012},
{"r":79339,"d":1,"s":0.074,"a":-0.013},
{"r":79413,"d":1.1,"s":0.071,"a":-0.014},
{"r":79459,"d":1.2,"s":0.069,"a":-0.014},
{"r":79517,"d":1.3,"s":0.066,"a":-0.015},
{"r":79598,"d":1.4,"s":0.062,"a":-0.015},
{"r":79795,"d":1.5,"s":0.051,"a":-0.015},
{"r":80421,"d":1.4,"s":0.021,"a":-0.007},
{"r":80627,"d":1.3,"s":0.015,"a":-0.005},
{"r":80720,"d":1.2,"s":0.013,"a":-0.005},
{"r":80806,"d":1.1,"s":0.011,"a":-0.005},
{"r":81033,"d":1.2,"s":0.007,"a":-0.005},
{"r":81365,"d":1.1,"s":0.001,"a":0.001},
{"r":81468,"d":1,"s":0,"a":0.003},
{"r":81556,"d":0.9,"s":0.001,"a":0.003},
{"r":81620,"d":0.8,"s":0.002,"a":0.003},
{"r":81725,"d":0.7,"s":0.003,"a":0.003},
{"r":81952,"d":0.8,"s":0.005,"a":0.001},
{"r":82301,"d":0.9,"s":0.006,"a":0},
{"r":82377,"d":1,"s":0.006,"a":0},
{"r":82619,"d":0.9,"s":0.005,"a":0.001},
{"r":82956,"d":0.8,"s":0.006,"a":0},
{"r":83154,"d":0.9,"s":0.007,"a":-0.002},
{"r":83276,"d":1,"s":0.006,"a":-0.003},
{"r":83375,"d":1.1,"s":0.004,"a":-0.004},
{"r":83743,"d":1.2,"s":-0.001,"a":-0.007},
{"r":83892,"d":1.3,"s":-0.005,"a":-0.007},
{"r":84030,"d":1.4,"s":-0.009,"a":-0.006},
{"r":84077,"d":1.3,"s":-0.01,"a":-0.005},
{"r":84282,"d":1.2,"s":-0.015,"a":-0.003},
{"r":84433,"d":1.1,"s":-0.017,"a":-0.003},
{"r":84647,"d":1,"s":-0.02,"a":-0.004},
{"r":84702,"d":1.1,"s":-0.021,"a":-0.004},
{"r":84802,"d":1,"s":-0.022,"a":-0.004},
{"r":84877,"d":1.1,"s":-0.024,"a":-0.004},
{"r":84961,"d":1.2,"s":-0.025,"a":-0.003},
{"r":85023,"d":1.1,"s":-0.026,"a":-0.002},
{"r":85256,"d":1,"s":-0.029,"a":0},
{"r":85404,"d":0.9,"s":-0.03,"a":0.002},
{"r":85492,"d":0.8,"s":-0.03,"a":0.003},
{"r":85614,"d":0.7,"s":-0.028,"a":0.002},
{"r":85717,"d":0.6,"s":-0.028,"a":0},
{"r":85810,"d":0.7,"s":-0.027,"a":-0.001},
{"r":86074,"d":0.8,"s":-0.028,"a":-0.006},
{"r":86127,"d":0.9,"s":-0.029,"a":-0.006},
{"r":86179,"d":1,"s":-0.03,"a":-0.006},
{"r":86262,"d":1.1,"s":-0.032,"a":-0.005},
{"r":86518,"d":1,"s":-0.038,"a":-0.001},
{"r":86644,"d":0.9,"s":-0.039,"a":0},
{"r":86681,"d":0.8,"s":-0.039,"a":0},
{"r":86792,"d":0.7,"s":-0.04,"a":0},
{"r":86975,"d":0.6,"s":-0.04,"a":0},
{"r":87031,"d":0.7,"s":-0.04,"a":0},
{"r":87246,"d":0.6,"s":-0.04,"a":-0.001},
{"r":87492,"d":0.7,"s":-0.042,"a":-0.007},
{"r":87663,"d":0.8,"s":-0.046,"a":-0.009},
{"r":87744,"d":0.9,"s":-0.048,"a":-0.009},
{"r":87794,"d":1,"s":-0.05,"a":-0.009},
{"r":88150,"d":0.9,"s":-0.061,"a":-0.002},
{"r":88241,"d":0.8,"s":-0.063,"a":-0.001},
{"r":88304,"d":0.7,"s":-0.064,"a":0},
{"r":88357,"d":0.6,"s":-0.064,"a":0},
{"r":88462,"d":0.5,"s":-0.065,"a":0},
{"r":88563,"d":0.4,"s":-0.065,"a":0},
{"r":89118,"d":0.3,"s":-0.068,"a":0.002},
{"r":89330,"d":0.2,"s":-0.067,"a":0.003},
{"r":89393,"d":0.1,"s":-0.066,"a":0.003},
{"r":89458,"d":0,"s":-0.065,"a":0.003},
{"r":89932,"d":0.1,"s":-0.064,"a":-0.005},
{"r":89999,"d":0.2,"s":-0.065,"a":-0.005},
{"r":90062,"d":0.3,"s":-0.066,"a":-0.006},
{"r":90757,"d":0.2,"s":-0.082,"a":-0.003},
{"r":90818,"d":0.1,"s":-0.083,"a":-0.002},
{"r":90894,"d":0,"s":-0.083,"a":-0.002},
{"r":91122,"d":-0.1,"s":-0.086,"a":-0.003},
{"r":91752,"d":-0.2,"s":-0.096,"a":0},
{"r":91797,"d":-0.1,"s":-0.096,"a":0},
{"r":91826,"d":-0.2,"s":-0.097,"a":0},
{"r":91911,"d":-0.3,"s":-0.097,"a":0.002},
{"r":91972,"d":-0.4,"s":-0.097,"a":0.003},
{"r":92027,"d":-0.5,"s":-0.097,"a":0.005},
{"r":92213,"d":-0.6,"s":-0.095,"a":0.009},
{"r":92257,"d":-0.7,"s":-0.094,"a":0.01},
{"r":92317,"d":-0.8,"s":-0.093,"a":0.01},
{"r":92366,"d":-0.9,"s":-0.091,"a":0.009},
{"r":92418,"d":-1,"s":-0.089,"a":0.009},
{"r":92476,"d":-1.1,"s":-0.087,"a":0.007},
{"r":92540,"d":-1.2,"s":-0.085,"a":0.006},
{"r":92675,"d":-1.1,"s":-0.081,"a":0.004},
{"r":92756,"d":-1,"s":-0.08,"a":0.005},
{"r":92843,"d":-0.9,"s":-0.079,"a":0.006},
{"r":93075,"d":-1,"s":-0.075,"a":0.009},
{"r":93143,"d":-1.1,"s":-0.073,"a":0.009},
{"r":93205,"d":-1.2,"s":-0.071,"a":0.009},
{"r":93268,"d":-1.3,"s":-0.069,"a":0.008},
{"r":93699,"d":-1.2,"s":-0.058,"a":0.007},
{"r":93933,"d":-1.3,"s":-0.053,"a":0.006},
{"r":94084,"d":-1.4,"s":-0.049,"a":0.004},
{"r":94168,"d":-1.3,"s":-0.048,"a":0.004},
{"r":94376,"d":-1.2,"s":-0.045,"a":0.006},
{"r":94601,"d":-1.3,"s":-0.041,"a":0.012},
{"r":94684,"d":-1.4,"s":-0.039,"a":0.013},
{"r":94757,"d":-1.5,"s":-0.036,"a":0.014},
{"r":94821,"d":-1.6,"s":-0.033,"a":0.014},
{"r":94876,"d":-1.7,"s":-0.031,"a":0.013},
{"r":94941,"d":-1.8,"s":-0.027,"a":0.012},
{"r":95004,"d":-1.9,"s":-0.024,"a":0.012},
{"r":95060,"d":-1.8,"s":-0.022,"a":0.011},
{"r":95190,"d":-1.7,"s":-0.017,"a":0.01},
{"r":95351,"d":-1.6,"s":-0.011,"a":0.007},
{"r":95676,"d":-1.5,"s":-0.004,"a":0},
{"r":95745,"d":-1.4,"s":-0.003,"a":0},
{"r":95799,"d":-1.3,"s":-0.003,"a":0.001},
{"r":95855,"d":-1.2,"s":-0.003,"a":0.002},
{"r":95943,"d":-1.1,"s":-0.004,"a":0.004},
{"r":96051,"d":-1.2,"s":-0.003,"a":0.005},
{"r":96135,"d":-1.3,"s":-0.002,"a":0.005},
{"r":96211,"d":-1.4,"s":0,"a":0.004},
{"r":96315,"d":-1.5,"s":0,"a":0.002},
{"r":96469,"d":-1.4,"s":0.003,"a":0},
{"r":96599,"d":-1.3,"s":0.003,"a":0.001},
{"r":96665,"d":-1.2,"s":0.003,"a":0.002},
{"r":96721,"d":-1.1,"s":0.002,"a":0.004},
{"r":96898,"d":-1.2,"s":0.004,"a":0.009},
{"r":96971,"d":-1.3,"s":0.005,"a":0.011},
{"r":97012,"d":-1.4,"s":0.006,"a":0.011},
{"r":97053,"d":-1.5,"s":0.008,"a":0.011},
{"r":97109,"d":-1.6,"s":0.01,"a":0.01},
{"r":97188,"d":-1.7,"s":0.013,"a":0.009},
{"r":97268,"d":-1.8,"s":0.016,"a":0.008},
{"r":97322,"d":-1.7,"s":0.017,"a":0.008},
{"r":97400,"d":-1.6,"s":0.02,"a":0.008},
{"r":97511,"d":-1.5,"s":0.022,"a":0.008},
{"r":98021,"d":-1.4,"s":0.035,"a":0.004},
{"r":98168,"d":-1.3,"s":0.037,"a":0.003},
{"r":98192,"d":-1.4,"s":0.038,"a":0.003},
{"r":98268,"d":-1.3,"s":0.039,"a":0.003},
{"r":98406,"d":-1.2,"s":0.04,"a":0.004},
{"r":98507,"d":-1.1,"s":0.041,"a":0.004},
{"r":98554,"d":-1.2,"s":0.041,"a":0.005},
{"r":98854,"d":-1.3,"s":0.046,"a":0.007},
{"r":99303,"d":-1.4,"s":0.058,"a":0.009},
{"r":99396,"d":-1.3,"s":0.061,"a":0.008},
{"r":99693,"d":-1.2,"s":0.069,"a":0.01},
{"r":99916,"d":-1.3,"s":0.076,"a":0.006},
{"r":100102,"d":-1.2,"s":0.081,"a":0},
{"r":100159,"d":-1.1,"s":0.082,"a":0},
{"r":100206,"d":-1,"s":0.082,"a":-0.001},
{"r":100247,"d":-0.9,"s":0.082,"a":-0.001},
{"r":100283,"d":-0.8,"s":0.082,"a":-0.001},
{"r":100328,"d":-0.7,"s":0.082,"a":-0.001},
{"r":100395,"d":-0.6,"s":0.081,"a":-0.001},
{"r":100584,"d":-0.5,"s":0.08,"a":0},
{"r":100894,"d":-0.6,"s":0.08,"a":0.006},
{"r":101005,"d":-0.7,"s":0.082,"a":0.006},
{"r":101072,"d":-0.8,"s":0.083,"a":0.005},
{"r":101309,"d":-0.7,"s":0.088,"a":0},
{"r":101399,"d":-0.6,"s":0.089,"a":-0.001},
{"r":101525,"d":-0.5,"s":0.089,"a":-0.003},
{"r":101585,"d":-0.4,"s":0.088,"a":-0.004},
{"r":101628,"d":-0.3,"s":0.088,"a":-0.004},
{"r":101696,"d":-0.2,"s":0.087,"a":-0.004},
{"r":101767,"d":-0.1,"s":0.086,"a":-0.003},
{"r":101845,"d":0,"s":0.084,"a":-0.002},
{"r":102030,"d":-0.1,"s":0.082,"a":-0.001},
{"r":102479,"d":0,"s":0.079,"a":-0.001},
{"r":102890,"d":0.1,"s":0.077,"a":-0.004},
{"r":103003,"d":0.2,"s":0.075,"a":-0.003},
{"r":103116,"d":0.3,"s":0.073,"a":-0.002},
{"r":103414,"d":0.2,"s":0.071,"a":0.001},
{"r":103518,"d":0.1,"s":0.071,"a":0.001},
{"r":103866,"d":0.2,"s":0.072,"a":-0.002},
{"r":103958,"d":0.3,"s":0.072,"a":-0.003},
{"r":104051,"d":0.4,"s":0.071,"a":-0.004},
{"r":104149,"d":0.5,"s":0.069,"a":-0.004},
{"r":104323,"d":0.6,"s":0.066,"a":-0.003},
{"r":104690,"d":0.5,"s":0.062,"a":0},
{"r":105147,"d":0.6,"s":0.06,"a":-0.005},
{"r":105316,"d":0.7,"s":0.058,"a":-0.007},
{"r":105406,"d":0.8,"s":0.056,"a":-0.007},
{"r":105456,"d":0.9,"s":0.054,"a":-0.006},
{"r":105524,"d":1,"s":0.052,"a":-0.006},
{"r":105666,"d":0.9,"s":0.049,"a":-0.006},
{"r":105835,"d":1,"s":0.045,"a":-0.006},
{"r":106565,"d":1.1,"s":0.028,"a":-0.006},
{"r":106745,"d":1,"s":0.024,"a":-0.008},
{"r":106925,"d":1.1,"s":0.019,"a":-0.009},
{"r":107029,"d":1.2,"s":0.016,"a":-0.008},
{"r":107136,"d":1.3,"s":0.012,"a":-0.007},
{"r":107258,"d":1.2,"s":0.008,"a":-0.006},
{"r":107421,"d":1.1,"s":0.004,"a":-0.007},
{"r":107541,"d":1,"s":0.002,"a":-0.009},
{"r":107634,"d":1.1,"s":0,"a":-0.01},
{"r":107730,"d":1.2,"s":-0.003,"a":-0.01},
{"r":107814,"d":1.3,"s":-0.006,"a":-0.01},
{"r":108202,"d":1.2,"s":-0.02,"a":-0.006},
{"r":108319,"d":1.1,"s":-0.023,"a":-0.006},
{"r":108475,"d":1,"s":-0.026,"a":-0.004},
{"r":108528,"d":1.1,"s":-0.028,"a":-0.004},
{"r":108659,"d":1,"s":-0.03,"a":-0.003},
{"r":108766,"d":0.9,"s":-0.031,"a":-0.004},
{"r":109147,"d":1,"s":-0.038,"a":-0.004},
{"r":109234,"d":0.9,"s":-0.039,"a":-0.004},
{"r":109640,"d":0.8,"s":-0.046,"a":-0.003},
{"r":109823,"d":0.7,"s":-0.048,"a":-0.003},
{"r":109902,"d":0.8,"s":-0.049,"a":-0.003},
{"r":109986,"d":0.7,"s":-0.05,"a":-0.002},
{"r":110355,"d":0.6,"s":-0.054,"a":-0.001},
{"r":110670,"d":0.5,"s":-0.056,"a":0.001},
{"r":110784,"d":0.4,"s":-0.056,"a":0.001},
{"r":110885,"d":0.3,"s":-0.055,"a":0.001},
{"r":111435,"d":0.4,"s":-0.055,"a":-0.003},
{"r":111572,"d":0.5,"s":-0.057,"a":-0.002},
{"r":111630,"d":0.4,"s":-0.058,"a":-0.002},
{"r":111949,"d":0.3,"s":-0.061,"a":-0.001},
{"r":112158,"d":0.4,"s":-0.063,"a":0},
{"r":112200,"d":0.3,"s":-0.063,"a":0},
{"r":112280,"d":0.2,"s":-0.063,"a":0},
{"r":112340,"d":0.1,"s":-0.063,"a":0},
{"r":112423,"d":0,"s":-0.063,"a":-0.001},
{"r":112538,"d":0.1,"s":-0.063,"a":-0.002},
{"r":112723,"d":0.2,"s":-0.065,"a":-0.003},
{"r":112762,"d":0.1,"s":-0.065,"a":-0.003},
{"r":112863,"d":0.2,"s":-0.066,"a":-0.003},
{"r":113136,"d":0.1,"s":-0.07,"a":-0.004},
{"r":113611,"d":0,"s":-0.078,"a":-0.003},
{"r":113897,"d":-0.1,"s":-0.082,"a":-0.001},
{"r":114100,"d":-0.2,"s":-0.083,"a":0.001},
{"r":114219,"d":-0.3,"s":-0.084,"a":0.004},
{"r":114373,"d":-0.4,"s":-0.083,"a":0.009},
{"r":114442,"d":-0.5,"s":-0.081,"a":0.01},
{"r":114499,"d":-0.6,"s":-0.08,"a":0.01},
{"r":114542,"d":-0.7,"s":-0.079,"a":0.01},
{"r":114583,"d":-0.8,"s":-0.077,"a":0.01},
{"r":114632,"d":-0.9,"s":-0.076,"a":0.01},
{"r":114791,"d":-1,"s":-0.07,"a":0.007},
{"r":115037,"d":-0.9,"s":-0.063,"a":0.001},
{"r":115143,"d":-0.8,"s":-0.062,"a":0.001},
{"r":115217,"d":-0.7,"s":-0.062,"a":0.001},
{"r":115311,"d":-0.6,"s":-0.062,"a":0.002},
{"r":115540,"d":-0.7,"s":-0.061,"a":0.005},
{"r":115603,"d":-0.8,"s":-0.06,"a":0.005},
{"r":115669,"d":-0.9,"s":-0.058,"a":0.005},
{"r":115733,"d":-1,"s":-0.057,"a":0.004},
{"r":115971,"d":-0.9,"s":-0.053,"a":0.005},
{"r":116224,"d":-1,"s":-0.049,"a":0.009},
{"r":116298,"d":-1.1,"s":-0.047,"a":0.01},
{"r":116366,"d":-1.2,"s":-0.045,"a":0.011},
{"r":116528,"d":-1.3,"s":-0.04,"a":0.012},
{"r":116666,"d":-1.4,"s":-0.034,"a":0.013},
{"r":116867,"d":-1.5,"s":-0.025,"a":0.012},
{"r":117161,"d":-1.4,"s":-0.014,"a":0.005},
{"r":117262,"d":-1.3,"s":-0.012,"a":0.004},
{"r":117344,"d":-1.2,"s":-0.01,"a":0.004},
{"r":117425,"d":-1.1,"s":-0.009,"a":0.004},
{"r":117533,"d":-1,"s":-0.008,"a":0.005},
{"r":117600,"d":-1.1,"s":-0.007,"a":0.006},
{"r":117793,"d":-1.2,"s":-0.004,"a":0.008},
{"r":117975,"d":-1.3,"s":0,"a":0.01},
{"r":118250,"d":-1.4,"s":0.009,"a":0.011},
{"r":118308,"d":-1.5,"s":0.012,"a":0.011},
{"r":118523,"d":-1.4,"s":0.02,"a":0.006},
{"r":118688,"d":-1.3,"s":0.024,"a":0.002},
{"r":118793,"d":-1.2,"s":0.025,"a":0},
{"r":118844,"d":-1.1,"s":0.026,"a":0},
{"r":118893,"d":-1,"s":0.026,"a":0},
{"r":118939,"d":-0.9,"s":0.026,"a":0},
{"r":119127,"d":-0.8,"s":0.026,"a":0.002},
{"r":119218,"d":-0.9,"s":0.026,"a":0.002},
{"r":119478,"d":-1,"s":0.028,"a":0.003},
{"r":119716,"d":-0.9,"s":0.03,"a":0.003},
{"r":120023,"d":-1,"s":0.034,"a":0.007},
{"r":120281,"d":-1.1,"s":0.039,"a":0.012},
{"r":120466,"d":-1.2,"s":0.046,"a":0.013},
{"r":120573,"d":-1.3,"s":0.051,"a":0.012},
{"r":120672,"d":-1.4,"s":0.056,"a":0.01},
{"r":120797,"d":-1.3,"s":0.061,"a":0.007},
{"r":120885,"d":-1.2,"s":0.063,"a":0.006},
{"r":120931,"d":-1.1,"s":0.064,"a":0.006},
{"r":120983,"d":-1,"s":0.066,"a":0.006},
{"r":121061,"d":-0.9,"s":0.067,"a":0.006},
{"r":121254,"d":-0.8,"s":0.071,"a":0.008},
{"r":121456,"d":-0.9,"s":0.076,"a":0.008},
{"r":121739,"d":-0.8,"s":0.083,"a":0.005},
{"r":121852,"d":-0.7,"s":0.085,"a":0.005},
{"r":121941,"d":-0.6,"s":0.087,"a":0.006},
{"r":122420,"d":-0.5,"s":0.096,"a":0.004},
{"r":122521,"d":-0.4,"s":0.097,"a":0.003},
{"r":122817,"d":-0.3,"s":0.101,"a":0},
{"r":122886,"d":-0.2,"s":0.101,"a":0},
{"r":122996,"d":-0.1,"s":0.101,"a":-0.001},
{"r":123103,"d":0,"s":0.1,"a":-0.002},
{"r":123193,"d":0.1,"s":0.099,"a":-0.002},
{"r":123258,"d":0.2,"s":0.099,"a":-0.002},
{"r":123309,"d":0.1,"s":0.098,"a":-0.002},
{"r":123396,"d":0.2,"s":0.097,"a":-0.002},
{"r":123507,"d":0.3,"s":0.096,"a":-0.003},
{"r":123674,"d":0.2,"s":0.094,"a":-0.003},
{"r":123756,"d":0.3,"s":0.093,"a":-0.003},
{"r":123857,"d":0.4,"s":0.092,"a":-0.003},
{"r":123927,"d":0.5,"s":0.091,"a":-0.004},
{"r":123985,"d":0.4,"s":0.09,"a":-0.004},
{"r":124135,"d":0.5,"s":0.087,"a":-0.005},
{"r":124305,"d":0.6,"s":0.084,"a":-0.003},
{"r":124439,"d":0.7,"s":0.082,"a":-0.002},
{"r":124535,"d":0.6,"s":0.081,"a":-0.003},
{"r":124629,"d":0.5,"s":0.08,"a":-0.003},
{"r":124739,"d":0.6,"s":0.079,"a":-0.004},
{"r":124901,"d":0.7,"s":0.076,"a":-0.003},
{"r":124978,"d":0.8,"s":0.074,"a":-0.001},
{"r":125239,"d":0.7,"s":0.072,"a":0},
{"r":125324,"d":0.6,"s":0.072,"a":-0.001},
{"r":125401,"d":0.5,"s":0.072,"a":-0.002},
{"r":125493,"d":0.6,"s":0.072,"a":-0.003},
{"r":125556,"d":0.7,"s":0.071,"a":-0.003},
{"r":125616,"d":0.8,"s":0.071,"a":-0.003},
{"r":125738,"d":0.9,"s":0.069,"a":-0.004},
{"r":126026,"d":1,"s":0.065,"a":-0.007},
{"r":126253,"d":1.1,"s":0.059,"a":-0.01},
{"r":126317,"d":1.2,"s":0.057,"a":-0.011},
{"r":126373,"d":1.3,"s":0.055,"a":-0.011},
{"r":126460,"d":1.4,"s":0.051,"a":-0.011},
{"r":126737,"d":1.5,"s":0.041,"a":-0.008},
{"r":126802,"d":1.4,"s":0.038,"a":-0.008},
{"r":127011,"d":1.3,"s":0.032,"a":-0.005},
{"r":127337,"d":1.2,"s":0.025,"a":-0.002},
{"r":127443,"d":1.1,"s":0.024,"a":-0.001},
{"r":127924,"d":1,"s":0.022,"a":0.002},
{"r":128072,"d":0.9,"s":0.024,"a":0.001},
{"r":128335,"d":1,"s":0.025,"a":-0.002},
{"r":128432,"d":1.1,"s":0.024,"a":-0.003},
{"r":128500,"d":1.2,"s":0.023,"a":-0.004},
{"r":128698,"d":1.3,"s":0.02,"a":-0.007},
{"r":128876,"d":1.4,"s":0.016,"a":-0.009},
{"r":129011,"d":1.5,"s":0.012,"a":-0.009},
{"r":129157,"d":1.6,"s":0.007,"a":-0.008},
{"r":129386,"d":1.5,"s":0,"a":-0.005},
{"r":129583,"d":1.4,"s":-0.004,"a":-0.004},
{"r":129717,"d":1.3,"s":-0.006,"a":-0.004},
{"r":130115,"d":1.4,"s":-0.014,"a":-0.007},
{"r":130229,"d":1.5,"s":-0.017,"a":-0.007},
{"r":130359,"d":1.4,"s":-0.02,"a":-0.006},
{"r":130823,"d":1.3,"s":-0.031,"a":-0.006},
{"r":131277,"d":1.4,"s":-0.042,"a":-0.008},
{"r":131676,"d":1.3,"s":-0.054,"a":-0.007},
{"r":131996,"d":1.2,"s":-0.063,"a":-0.005},
{"r":132184,"d":1.1,"s":-0.067,"a":-0.006},
{"r":132303,"d":1,"s":-0.069,"a":-0.005},
{"r":132366,"d":1.1,"s":-0.071,"a":-0.005},
{"r":132581,"d":1,"s":-0.075,"a":-0.005},
{"r":132779,"d":0.9,"s":-0.079,"a":-0.004},
{"r":133141,"d":0.8,"s":-0.085,"a":-0.003},
{"r":133222,"d":0.7,"s":-0.086,"a":-0.004},
{"r":133334,"d":0.6,"s":-0.087,"a":-0.006},
{"r":133415,"d":0.7,"s":-0.089,"a":-0.006},
{"r":133524,"d":0.8,"s":-0.091,"a":-0.005},
{"r":133775,"d":0.7,"s":-0.096,"a":-0.001},
{"r":133851,"d":0.6,"s":-0.097,"a":-0.001},
{"r":133921,"d":0.5,"s":-0.098,"a":0},
{"r":133987,"d":0.4,"s":-0.098,"a":-0.001},
{"r":134167,"d":0.3,"s":-0.099,"a":-0.002},
{"r":134533,"d":0.4,"s":-0.104,"a":-0.005},
{"r":134652,"d":0.5,"s":-0.106,"a":-0.004},
{"r":134720,"d":0.4,"s":-0.108,"a":-0.003},
{"r":134827,"d":0.3,"s":-0.11,"a":-0.002},
{"r":134913,"d":0.2,"s":-0.111,"a":-0.001},
{"r":135039,"d":0.1,"s":-0.112,"a":0},
{"r":135161,"d":0,"s":-0.113,"a":0.001},
{"r":135361,"d":-0.1,"s":-0.113,"a":0.004},
{"r":135433,"d":-0.2,"s":-0.112,"a":0.004},
{"r":135505,"d":-0.3,"s":-0.112,"a":0.004},
{"r":135564,"d":-0.4,"s":-0.111,"a":0.003},
{"r":135648,"d":-0.5,"s":-0.11,"a":0.003},
{"r":135838,"d":-0.4,"s":-0.108,"a":0.001},
{"r":135928,"d":-0.5,"s":-0.107,"a":0.001},
{"r":136182,"d":-0.4,"s":-0.106,"a":0},
{"r":136257,"d":-0.5,"s":-0.106,"a":0},
{"r":136383,"d":-0.6,"s":-0.106,"a":-0.001},
{"r":136552,"d":-0.5,"s":-0.107,"a":-0.003},
{"r":137236,"d":-0.6,"s":-0.119,"a":-0.003},
{"r":137493,"d":-0.7,"s":-0.122,"a":0.005},
{"r":137551,"d":-0.8,"s":-0.122,"a":0.007},
{"r":137615,"d":-0.9,"s":-0.121,"a":0.008},
{"r":137657,"d":-1,"s":-0.12,"a":0.008},
{"r":137690,"d":-1.1,"s":-0.12,"a":0.008},
{"r":137719,"d":-1.2,"s":-0.119,"a":0.008},
{"r":137746,"d":-1.3,"s":-0.118,"a":0.008},
{"r":137777,"d":-1.4,"s":-0.117,"a":0.008},
{"r":137815,"d":-1.5,"s":-0.116,"a":0.007},
{"r":138343,"d":-1.6,"s":-0.103,"a":0.01},
{"r":138457,"d":-1.7,"s":-0.1,"a":0.01},
{"r":138543,"d":-1.8,"s":-0.097,"a":0.009},
{"r":138721,"d":-1.9,"s":-0.091,"a":0.008},
{"r":138825,"d":-1.8,"s":-0.088,"a":0.008},
{"r":139073,"d":-1.9,"s":-0.082,"a":0.007},
{"r":139232,"d":-1.8,"s":-0.078,"a":0.008},
{"r":139272,"d":-1.9,"s":-0.077,"a":0.009},
{"r":139525,"d":-2,"s":-0.07,"a":0.014},
{"r":139637,"d":-2.1,"s":-0.065,"a":0.016},
{"r":139713,"d":-2.2,"s":-0.062,"a":0.016},
{"r":139763,"d":-2.3,"s":-0.059,"a":0.015},
{"r":139805,"d":-2.4,"s":-0.057,"a":0.015},
{"r":139876,"d":-2.5,"s":-0.053,"a":0.014},
{"r":139996,"d":-2.4,"s":-0.047,"a":0.011},
{"r":140239,"d":-2.3,"s":-0.037,"a":0.006},
{"r":140302,"d":-2.2,"s":-0.036,"a":0.006},
{"r":140411,"d":-2.1,"s":-0.033,"a":0.007},
{"r":140471,"d":-2,"s":-0.032,"a":0.008},
{"r":140678,"d":-2.1,"s":-0.028,"a":0.011},
{"r":140779,"d":-2.2,"s":-0.024,"a":0.012},
{"r":140848,"d":-2.3,"s":-0.022,"a":0.011},
{"r":140939,"d":-2.4,"s":-0.018,"a":0.01},
{"r":141244,"d":-2.3,"s":-0.008,"a":0.005},
{"r":141299,"d":-2.2,"s":-0.007,"a":0.005},
{"r":141373,"d":-2.1,"s":-0.006,"a":0.005},
{"r":141836,"d":-2.2,"s":0.002,"a":0.01},
{"r":142095,"d":-2.3,"s":0.011,"a":0.011},
{"r":142169,"d":-2.4,"s":0.014,"a":0.011},
{"r":142494,"d":-2.3,"s":0.025,"a":0.007},
{"r":142577,"d":-2.2,"s":0.027,"a":0.007},
{"r":142658,"d":-2.1,"s":0.029,"a":0.007},
{"r":143007,"d":-2.2,"s":0.037,"a":0.01},
{"r":143239,"d":-2.3,"s":0.045,"a":0.011},
{"r":143298,"d":-2.2,"s":0.047,"a":0.011},
{"r":143692,"d":-2.3,"s":0.063,"a":0.015},
{"r":143783,"d":-2.4,"s":0.068,"a":0.015},
{"r":143988,"d":-2.3,"s":0.078,"a":0.013},
{"r":144098,"d":-2.2,"s":0.083,"a":0.012},
{"r":144110,"d":-2.3,"s":0.084,"a":0.012},
{"r":144116,"d":-2.2,"s":0.084,"a":0.012},
{"r":144121,"d":-2.3,"s":0.084,"a":0.012},
{"r":144123,"d":-2.2,"s":0.084,"a":0.012},
{"r":144265,"d":-2.1,"s":0.09,"a":0.012},
{"r":144447,"d":-2,"s":0.097,"a":0.011},
{"r":144666,"d":-1.9,"s":0.105,"a":0.011},
{"r":144860,"d":-1.8,"s":0.112,"a":0.012},
{"r":144948,"d":-1.7,"s":0.115,"a":0.013},
{"r":144979,"d":-1.8,"s":0.117,"a":0.013},
{"r":145108,"d":-1.9,"s":0.122,"a":0.012},
{"r":145195,"d":-1.8,"s":0.126,"a":0.011},
{"r":145388,"d":-1.7,"s":0.134,"a":0.01},
{"r":145472,"d":-1.6,"s":0.136,"a":0.009},
{"r":145571,"d":-1.5,"s":0.14,"a":0.009},
{"r":145752,"d":-1.4,"s":0.145,"a":0.01},
{"r":145827,"d":-1.3,"s":0.147,"a":0.01},
{"r":146226,"d":-1.2,"s":0.16,"a":0.007},
{"r":146294,"d":-1.1,"s":0.162,"a":0.006},
{"r":146373,"d":-1,"s":0.164,"a":0.005},
{"r":146498,"d":-0.9,"s":0.166,"a":0.003},
{"r":146602,"d":-0.8,"s":0.168,"a":0.002},
{"r":146699,"d":-0.7,"s":0.169,"a":0},
{"r":146775,"d":-0.6,"s":0.169,"a":0},
{"r":146863,"d":-0.5,"s":0.17,"a":-0.002},
{"r":146934,"d":-0.4,"s":0.169,"a":-0.002},
{"r":147011,"d":-0.3,"s":0.169,"a":-0.003},
{"r":147087,"d":-0.2,"s":0.168,"a":-0.003},
{"r":147143,"d":-0.1,"s":0.167,"a":-0.003},
{"r":147210,"d":0,"s":0.166,"a":-0.004},
{"r":147426,"d":0.1,"s":0.163,"a":-0.008},
{"r":147566,"d":0.2,"s":0.16,"a":-0.011},
{"r":147619,"d":0.3,"s":0.158,"a":-0.012},
{"r":147669,"d":0.4,"s":0.156,"a":-0.012},
{"r":147719,"d":0.5,"s":0.154,"a":-0.012},
{"r":147765,"d":0.6,"s":0.152,"a":-0.011},
{"r":147825,"d":0.7,"s":0.15,"a":-0.01},
{"r":147889,"d":0.8,"s":0.147,"a":-0.01},
{"r":148101,"d":0.7,"s":0.139,"a":-0.008},
{"r":148240,"d":0.8,"s":0.135,"a":-0.009},
{"r":148326,"d":0.7,"s":0.132,"a":-0.01},
{"r":148494,"d":0.8,"s":0.127,"a":-0.014},
{"r":148573,"d":0.9,"s":0.124,"a":-0.015},
{"r":148623,"d":1,"s":0.121,"a":-0.015},
{"r":148663,"d":1.1,"s":0.119,"a":-0.015},
{"r":148711,"d":1.2,"s":0.117,"a":-0.016},
{"r":148806,"d":1.3,"s":0.112,"a":-0.016},
{"r":149033,"d":1.4,"s":0.099,"a":-0.018},
{"r":149142,"d":1.5,"s":0.092,"a":-0.017},
{"r":149229,"d":1.6,"s":0.087,"a":-0.016},
{"r":149544,"d":1.5,"s":0.069,"a":-0.011},
{"r":149631,"d":1.4,"s":0.065,"a":-0.011},
{"r":150258,"d":1.3,"s":0.044,"a":-0.006},
{"r":150376,"d":1.2,"s":0.041,"a":-0.007},
{"r":150582,"d":1.3,"s":0.036,"a":-0.009},
{"r":150673,"d":1.4,"s":0.033,"a":-0.009},
{"r":150813,"d":1.5,"s":0.029,"a":-0.008},
{"r":151006,"d":1.4,"s":0.023,"a":-0.009},
{"r":151231,"d":1.5,"s":0.016,"a":-0.009},
{"r":151676,"d":1.4,"s":0.003,"a":-0.007},
{"r":152252,"d":1.5,"s":-0.012,"a":-0.009},
{"r":152642,"d":1.4,"s":-0.024,"a":-0.007},
{"r":152980,"d":1.3,"s":-0.032,"a":-0.001},
{"r":153172,"d":1.2,"s":-0.034,"a":0.002},
{"r":153233,"d":1.1,"s":-0.034,"a":0.002},
{"r":153278,"d":1,"s":-0.034,"a":0.002},
{"r":153333,"d":0.9,"s":-0.033,"a":0.002},
{"r":153399,"d":0.8,"s":-0.033,"a":0.001},
{"r":153629,"d":0.9,"s":-0.031,"a":0},
{"r":153892,"d":1,"s":-0.032,"a":-0.002},
{"r":154765,"d":1.1,"s":-0.043,"a":-0.007},
{"r":155294,"d":1,"s":-0.055,"a":-0.001},
{"r":155397,"d":0.9,"s":-0.056,"a":0},
{"r":155512,"d":0.8,"s":-0.057,"a":0},
{"r":155575,"d":0.7,"s":-0.057,"a":-0.001},
{"r":155660,"d":0.6,"s":-0.056,"a":-0.002},
{"r":155932,"d":0.7,"s":-0.058,"a":-0.004},
{"r":155993,"d":0.8,"s":-0.059,"a":-0.004},
{"r":156278,"d":0.7,"s":-0.063,"a":0},
{"r":156358,"d":0.6,"s":-0.063,"a":0},
{"r":156491,"d":0.5,"s":-0.063,"a":0.002},
{"r":156558,"d":0.4,"s":-0.062,"a":0.002},
{"r":156713,"d":0.3,"s":-0.061,"a":0.005},
{"r":156900,"d":0.2,"s":-0.058,"a":0.008},
{"r":156978,"d":0.1,"s":-0.056,"a":0.009},
{"r":157048,"d":0,"s":-0.054,"a":0.009},
{"r":157195,"d":-0.1,"s":-0.048,"a":0.009},
{"r":157258,"d":-0.2,"s":-0.046,"a":0.01},
{"r":157667,"d":-0.3,"s":-0.029,"a":0.009},
{"r":157772,"d":-0.4,"s":-0.025,"a":0.006},
{"r":157900,"d":-0.3,"s":-0.02,"a":0.003},
{"r":157993,"d":-0.2,"s":-0.018,"a":0.002},
{"r":158069,"d":-0.1,"s":-0.016,"a":0.002},
{"r":158134,"d":0,"s":-0.015,"a":0.002},
{"r":159320,"d":-0.1,"s":0,"a":0},
{"r":159411,"d":-0.2,"s":0,"a":0}
]
